prefect_geopandas_serializer/__init__.py
prefect_geopandas_serializer/serializers.py
prefect_geopandas_serializer-0.1.0.dist-info/LICENSE
prefect_geopandas_serializer-0.1.0.dist-info/WHEEL
prefect_geopandas_serializer-0.1.0.dist-info/METADATA
prefect_geopandas_serializer-0.1.0.dist-info/RECORD
