Metadata-Version: 2.1
Name: prefect-geopandas-serializer
Version: 0.1.0
Summary: PandasSerializer adapted for GeoPandas
License: MIT
Author: Rowan Molony
Author-email: rowan.molony@codema.ie
Requires-Python: >=3.7,<4.0
Classifier: License :: OSI Approved :: MIT License
Classifier: Programming Language :: Python :: 3
Classifier: Programming Language :: Python :: 3.7
Classifier: Programming Language :: Python :: 3.8
Classifier: Programming Language :: Python :: 3.9
Requires-Dist: geopandas (>=0.9.0,<0.10.0)
Requires-Dist: prefect (>=0.15.3,<0.16.0)
Requires-Dist: pyarrow (>=5.0.0,<6.0.0)
